__init__.py
common/Messages.py
common/SerialDevices.py
common/__init__.py
common/enums.py
UofA_BAJA_Palatable9622-0.0.2.dist-info/LICENSE
UofA_BAJA_Palatable9622-0.0.2.dist-info/METADATA
UofA_BAJA_Palatable9622-0.0.2.dist-info/WHEEL
UofA_BAJA_Palatable9622-0.0.2.dist-info/top_level.txt
UofA_BAJA_Palatable9622-0.0.2.dist-info/RECORD
