Metadata-Version: 2.1
Name: UofA_BAJA_Palatable9622
Version: 0.0.2
Summary: packages for the UofA Baja team
Author-email: Alex Romero <bix.romero@gmail.com>
Project-URL: Homepage, https://github.com/UofA-BAJA/2023-2024-Firmware
Classifier: Programming Language :: Python :: 3
Classifier: License :: OSI Approved :: MIT License
Classifier: Operating System :: OS Independent
Requires-Python: >=3.8
License-File: LICENSE
